tests/__init__.py
tests/ae.py
tests/test.py
torchcoder/__init__.py
torchcoder/layers/__init__.py
torchcoder/layers/graphconvolution.py
torchcoder/models/TEST.py
torchcoder/models/__init__.py
torchcoder/models/ae.py
torchcoder/models/bivae.py
torchcoder/models/gae.py
torchcoder/models/gcnvae.py
torchcoder/optimizers/__init__.py
torchcoder/optimizers/optimizers.py
torchcoder-0.0.5.dist-info/LICENSE
torchcoder-0.0.5.dist-info/METADATA
torchcoder-0.0.5.dist-info/WHEEL
torchcoder-0.0.5.dist-info/top_level.txt
torchcoder-0.0.5.dist-info/RECORD
